{
    "directed": false,
    "multigraph": false,
    "graph": {},
    "nodes": [
        {
            "id": 51,
            "surface_type": "PlaneSurfaceType",
            "area": 0.36000000536441834,
            "normal_x": 0.0,
            "normal_y": 0.0,
            "normal_z": -1.0,
            "max_tangent_x": 1.0,
            "max_tangent_y": 0.0,
            "max_tangent_z": 0.0,
            "max_curvature": 0.0,
            "min_curvature": 0.0,
            "operation_label": "ExtrudeSide",
            "last_operation_label": true
        },
        {
            "id": 54,
            "surface_type": "PlaneSurfaceType",
            "area": 0.36000000536441834,
            "normal_x": 0.0,
            "normal_y": -1.0,
            "normal_z": 0.0,
            "max_tangent_x": 1.0,
            "max_tangent_y": 0.0,
            "max_tangent_z": -0.0,
            "max_curvature": 0.0,
            "min_curvature": 0.0,
            "operation_label": "ExtrudeSide",
            "last_operation_label": true
        },
        {
            "id": 53,
            "surface_type": "PlaneSurfaceType",
            "area": 0.36000000536441834,
            "normal_x": 0.0,
            "normal_y": 0.0,
            "normal_z": 1.0,
            "max_tangent_x": 1.0,
            "max_tangent_y": 0.0,
            "max_tangent_z": 0.0,
            "max_curvature": 0.0,
            "min_curvature": 0.0,
            "operation_label": "ExtrudeSide",
            "last_operation_label": true
        },
        {
            "id": 52,
            "surface_type": "PlaneSurfaceType",
            "area": 0.36000000536441834,
            "normal_x": 0.0,
            "normal_y": 1.0,
            "normal_z": 0.0,
            "max_tangent_x": 1.0,
            "max_tangent_y": 0.0,
            "max_tangent_z": 0.0,
            "max_curvature": 0.0,
            "min_curvature": 0.0,
            "operation_label": "ExtrudeSide",
            "last_operation_label": true
        },
        {
            "id": 50,
            "surface_type": "PlaneSurfaceType",
            "area": 3.240000096559525,
            "normal_x": 1.0,
            "normal_y": 0.0,
            "normal_z": 0.0,
            "max_tangent_x": -0.0,
            "max_tangent_y": 1.0,
            "max_tangent_z": 0.0,
            "max_curvature": 0.0,
            "min_curvature": 0.0,
            "operation_label": "ExtrudeEnd",
            "last_operation_label": true
        },
        {
            "id": 34,
            "surface_type": "PlaneSurfaceType",
            "area": 4.0,
            "normal_x": 0.0,
            "normal_y": -1.0,
            "normal_z": -0.0,
            "max_tangent_x": 0.0,
            "max_tangent_y": 0.0,
            "max_tangent_z": -1.0,
            "max_curvature": 0.0,
            "min_curvature": 0.0,
            "operation_label": "CutSide",
            "last_operation_label": false
        },
        {
            "id": 36,
            "surface_type": "PlaneSurfaceType",
            "area": 4.0,
            "normal_x": 1.0,
            "normal_y": 0.0,
            "normal_z": -0.0,
            "max_tangent_x": 0.0,
            "max_tangent_y": 0.0,
            "max_tangent_z": -1.0,
            "max_curvature": 0.0,
            "min_curvature": 0.0,
            "operation_label": "CutSide",
            "last_operation_label": false
        },
        {
            "id": 35,
            "surface_type": "PlaneSurfaceType",
            "area": 4.0,
            "normal_x": 0.0,
            "normal_y": 1.0,
            "normal_z": 0.0,
            "max_tangent_x": 0.0,
            "max_tangent_y": 0.0,
            "max_tangent_z": -1.0,
            "max_curvature": 0.0,
            "min_curvature": 0.0,
            "operation_label": "CutSide",
            "last_operation_label": false
        },
        {
            "id": 37,
            "surface_type": "PlaneSurfaceType",
            "area": 4.0,
            "normal_x": -1.0,
            "normal_y": 0.0,
            "normal_z": -0.0,
            "max_tangent_x": 0.0,
            "max_tangent_y": 0.0,
            "max_tangent_z": -1.0,
            "max_curvature": 0.0,
            "min_curvature": 0.0,
            "operation_label": "CutSide",
            "last_operation_label": false
        },
        {
            "id": 4,
            "surface_type": "PlaneSurfaceType",
            "area": 0.7599999034404745,
            "normal_x": 1.0,
            "normal_y": 0.0,
            "normal_z": 0.0,
            "max_tangent_x": 0.0,
            "max_tangent_y": 0.0,
            "max_tangent_z": 1.0,
            "max_curvature": 0.0,
            "min_curvature": 0.0,
            "operation_label": "ExtrudeSide",
            "last_operation_label": false
        },
        {
            "id": 5,
            "surface_type": "PlaneSurfaceType",
            "area": 2.8284271247461903,
            "normal_x": 0.7071067811865476,
            "normal_y": -0.7071067811865476,
            "normal_z": 0.0,
            "max_tangent_x": -0.0,
            "max_tangent_y": 0.0,
            "max_tangent_z": 1.0,
            "max_curvature": 0.0,
            "min_curvature": 0.0,
            "operation_label": "ExtrudeSide",
            "last_operation_label": false
        },
        {
            "id": 8,
            "surface_type": "PlaneSurfaceType",
            "area": 4.0,
            "normal_x": 0.0,
            "normal_y": -1.0,
            "normal_z": 0.0,
            "max_tangent_x": -0.0,
            "max_tangent_y": 0.0,
            "max_tangent_z": 1.0,
            "max_curvature": 0.0,
            "min_curvature": 0.0,
            "operation_label": "ExtrudeSide",
            "last_operation_label": false
        },
        {
            "id": 9,
            "surface_type": "PlaneSurfaceType",
            "area": 2.8284271247461903,
            "normal_x": -0.7071067811865476,
            "normal_y": -0.7071067811865476,
            "normal_z": 0.0,
            "max_tangent_x": 0.0,
            "max_tangent_y": 0.0,
            "max_tangent_z": 1.0,
            "max_curvature": 0.0,
            "min_curvature": 0.0,
            "operation_label": "ExtrudeSide",
            "last_operation_label": false
        },
        {
            "id": 2,
            "surface_type": "PlaneSurfaceType",
            "area": 4.0,
            "normal_x": -1.0,
            "normal_y": 0.0,
            "normal_z": 0.0,
            "max_tangent_x": 0.0,
            "max_tangent_y": 0.0,
            "max_tangent_z": 1.0,
            "max_curvature": 0.0,
            "min_curvature": 0.0,
            "operation_label": "ExtrudeSide",
            "last_operation_label": false
        },
        {
            "id": 3,
            "surface_type": "PlaneSurfaceType",
            "area": 2.8284271247461903,
            "normal_x": -0.7071067811865476,
            "normal_y": 0.7071067811865476,
            "normal_z": 0.0,
            "max_tangent_x": 0.0,
            "max_tangent_y": 0.0,
            "max_tangent_z": 1.0,
            "max_curvature": 0.0,
            "min_curvature": 0.0,
            "operation_label": "ExtrudeSide",
            "last_operation_label": false
        },
        {
            "id": 6,
            "surface_type": "PlaneSurfaceType",
            "area": 4.0,
            "normal_x": 0.0,
            "normal_y": 1.0,
            "normal_z": 0.0,
            "max_tangent_x": 0.0,
            "max_tangent_y": 0.0,
            "max_tangent_z": 1.0,
            "max_curvature": 0.0,
            "min_curvature": 0.0,
            "operation_label": "ExtrudeSide",
            "last_operation_label": false
        },
        {
            "id": 7,
            "surface_type": "PlaneSurfaceType",
            "area": 2.8284271247461903,
            "normal_x": 0.7071067811865476,
            "normal_y": 0.7071067811865476,
            "normal_z": 0.0,
            "max_tangent_x": 0.0,
            "max_tangent_y": 0.0,
            "max_tangent_z": 1.0,
            "max_curvature": 0.0,
            "min_curvature": 0.0,
            "operation_label": "ExtrudeSide",
            "last_operation_label": false
        },
        {
            "id": 1,
            "surface_type": "PlaneSurfaceType",
            "area": 10.0,
            "normal_x": 0.0,
            "normal_y": 0.0,
            "normal_z": 1.0,
            "max_tangent_x": 0.0,
            "max_tangent_y": 1.0,
            "max_tangent_z": 0.0,
            "max_curvature": 0.0,
            "min_curvature": 0.0,
            "operation_label": "ExtrudeEnd",
            "last_operation_label": false
        },
        {
            "id": 0,
            "surface_type": "PlaneSurfaceType",
            "area": 10.0,
            "normal_x": 0.0,
            "normal_y": 0.0,
            "normal_z": -1.0,
            "max_tangent_x": 0.0,
            "max_tangent_y": 1.0,
            "max_tangent_z": 0.0,
            "max_curvature": 0.0,
            "min_curvature": 0.0,
            "operation_label": "ExtrudeStart",
            "last_operation_label": false
        }
    ],
    "links": [
        {
            "id": 55,
            "source": 4,
            "target": 51,
            "curve_type": "Line3DCurveType",
            "length": 1.8000000268220901,
            "convexity": "Concave",
            "direction_x": 0.0,
            "direction_y": 0.0,
            "direction_z": 0.0,
            "curvature": 0.0
        },
        {
            "id": 56,
            "source": 52,
            "target": 51,
            "curve_type": "Line3DCurveType",
            "length": 0.20000000000000018,
            "convexity": "Convex",
            "direction_x": 0.0,
            "direction_y": 0.0,
            "direction_z": 0.0,
            "curvature": 0.0
        },
        {
            "id": 57,
            "source": 51,
            "target": 50,
            "curve_type": "Line3DCurveType",
            "length": 1.8000000268220901,
            "convexity": "Convex",
            "direction_x": 0.0,
            "direction_y": 0.0,
            "direction_z": 0.0,
            "curvature": 0.0
        },
        {
            "id": 58,
            "source": 54,
            "target": 51,
            "curve_type": "Line3DCurveType",
            "length": 0.20000000000000018,
            "convexity": "Convex",
            "direction_x": 0.0,
            "direction_y": 0.0,
            "direction_z": 0.0,
            "curvature": 0.0
        },
        {
            "id": 59,
            "source": 4,
            "target": 54,
            "curve_type": "Line3DCurveType",
            "length": 1.8000000268220901,
            "convexity": "Concave",
            "direction_x": 0.0,
            "direction_y": 0.0,
            "direction_z": 0.0,
            "curvature": 0.0
        },
        {
            "id": 60,
            "source": 54,
            "target": 50,
            "curve_type": "Line3DCurveType",
            "length": 1.8000000268220901,
            "convexity": "Convex",
            "direction_x": 0.0,
            "direction_y": 0.0,
            "direction_z": 0.0,
            "curvature": 0.0
        },
        {
            "id": 61,
            "source": 53,
            "target": 54,
            "curve_type": "Line3DCurveType",
            "length": 0.20000000000000018,
            "convexity": "Convex",
            "direction_x": 0.0,
            "direction_y": 0.0,
            "direction_z": 0.0,
            "curvature": 0.0
        },
        {
            "id": 62,
            "source": 4,
            "target": 53,
            "curve_type": "Line3DCurveType",
            "length": 1.8000000268220901,
            "convexity": "Concave",
            "direction_x": 0.0,
            "direction_y": 0.0,
            "direction_z": 0.0,
            "curvature": 0.0
        },
        {
            "id": 63,
            "source": 53,
            "target": 50,
            "curve_type": "Line3DCurveType",
            "length": 1.8000000268220901,
            "convexity": "Convex",
            "direction_x": 0.0,
            "direction_y": 0.0,
            "direction_z": 0.0,
            "curvature": 0.0
        },
        {
            "id": 64,
            "source": 52,
            "target": 53,
            "curve_type": "Line3DCurveType",
            "length": 0.20000000000000018,
            "convexity": "Convex",
            "direction_x": 0.0,
            "direction_y": 0.0,
            "direction_z": 0.0,
            "curvature": 0.0
        },
        {
            "id": 65,
            "source": 4,
            "target": 52,
            "curve_type": "Line3DCurveType",
            "length": 1.8000000268220901,
            "convexity": "Concave",
            "direction_x": 0.0,
            "direction_y": 0.0,
            "direction_z": 0.0,
            "curvature": 0.0
        },
        {
            "id": 66,
            "source": 52,
            "target": 50,
            "curve_type": "Line3DCurveType",
            "length": 1.8000000268220901,
            "convexity": "Convex",
            "direction_x": 0.0,
            "direction_y": 0.0,
            "direction_z": 0.0,
            "curvature": 0.0
        },
        {
            "id": 38,
            "source": 1,
            "target": 34,
            "curve_type": "Line3DCurveType",
            "length": 2.0,
            "convexity": "Convex",
            "direction_x": 0.0,
            "direction_y": 0.0,
            "direction_z": 0.0,
            "curvature": 0.0
        },
        {
            "id": 39,
            "source": 36,
            "target": 34,
            "curve_type": "Line3DCurveType",
            "length": 2.0,
            "convexity": "Concave",
            "direction_x": 0.0,
            "direction_y": 0.0,
            "direction_z": 0.0,
            "curvature": 0.0
        },
        {
            "id": 40,
            "source": 0,
            "target": 34,
            "curve_type": "Line3DCurveType",
            "length": 2.0,
            "convexity": "Convex",
            "direction_x": 0.0,
            "direction_y": 0.0,
            "direction_z": 0.0,
            "curvature": 0.0
        },
        {
            "id": 41,
            "source": 37,
            "target": 34,
            "curve_type": "Line3DCurveType",
            "length": 2.0,
            "convexity": "Concave",
            "direction_x": 0.0,
            "direction_y": 0.0,
            "direction_z": 0.0,
            "curvature": 0.0
        },
        {
            "id": 42,
            "source": 1,
            "target": 36,
            "curve_type": "Line3DCurveType",
            "length": 2.0,
            "convexity": "Convex",
            "direction_x": 0.0,
            "direction_y": 0.0,
            "direction_z": 0.0,
            "curvature": 0.0
        },
        {
            "id": 43,
            "source": 35,
            "target": 36,
            "curve_type": "Line3DCurveType",
            "length": 2.0,
            "convexity": "Concave",
            "direction_x": 0.0,
            "direction_y": 0.0,
            "direction_z": 0.0,
            "curvature": 0.0
        },
        {
            "id": 44,
            "source": 0,
            "target": 36,
            "curve_type": "Line3DCurveType",
            "length": 2.0,
            "convexity": "Convex",
            "direction_x": 0.0,
            "direction_y": 0.0,
            "direction_z": 0.0,
            "curvature": 0.0
        },
        {
            "id": 45,
            "source": 1,
            "target": 35,
            "curve_type": "Line3DCurveType",
            "length": 2.0,
            "convexity": "Convex",
            "direction_x": 0.0,
            "direction_y": 0.0,
            "direction_z": 0.0,
            "curvature": 0.0
        },
        {
            "id": 46,
            "source": 37,
            "target": 35,
            "curve_type": "Line3DCurveType",
            "length": 2.0,
            "convexity": "Concave",
            "direction_x": 0.0,
            "direction_y": 0.0,
            "direction_z": 0.0,
            "curvature": 0.0
        },
        {
            "id": 47,
            "source": 0,
            "target": 35,
            "curve_type": "Line3DCurveType",
            "length": 2.0,
            "convexity": "Convex",
            "direction_x": 0.0,
            "direction_y": 0.0,
            "direction_z": 0.0,
            "curvature": 0.0
        },
        {
            "id": 48,
            "source": 1,
            "target": 37,
            "curve_type": "Line3DCurveType",
            "length": 2.0,
            "convexity": "Convex",
            "direction_x": 0.0,
            "direction_y": 0.0,
            "direction_z": 0.0,
            "curvature": 0.0
        },
        {
            "id": 49,
            "source": 0,
            "target": 37,
            "curve_type": "Line3DCurveType",
            "length": 2.0,
            "convexity": "Convex",
            "direction_x": 0.0,
            "direction_y": 0.0,
            "direction_z": 0.0,
            "curvature": 0.0
        },
        {
            "id": 10,
            "source": 4,
            "target": 0,
            "curve_type": "Line3DCurveType",
            "length": 2.0,
            "convexity": "Convex",
            "direction_x": 0.0,
            "direction_y": 0.0,
            "direction_z": 0.0,
            "curvature": 0.0
        },
        {
            "id": 11,
            "source": 7,
            "target": 4,
            "curve_type": "Line3DCurveType",
            "length": 2.0,
            "convexity": "Convex",
            "direction_x": 0.0,
            "direction_y": 0.0,
            "direction_z": 0.0,
            "curvature": 0.0
        },
        {
            "id": 12,
            "source": 4,
            "target": 1,
            "curve_type": "Line3DCurveType",
            "length": 2.0,
            "convexity": "Convex",
            "direction_x": 0.0,
            "direction_y": 0.0,
            "direction_z": 0.0,
            "curvature": 0.0
        },
        {
            "id": 13,
            "source": 5,
            "target": 4,
            "curve_type": "Line3DCurveType",
            "length": 2.0,
            "convexity": "Convex",
            "direction_x": 0.0,
            "direction_y": 0.0,
            "direction_z": 0.0,
            "curvature": 0.0
        },
        {
            "id": 14,
            "source": 5,
            "target": 0,
            "curve_type": "Line3DCurveType",
            "length": 1.414213562373095,
            "convexity": "Convex",
            "direction_x": 0.0,
            "direction_y": 0.0,
            "direction_z": 0.0,
            "curvature": 0.0
        },
        {
            "id": 15,
            "source": 5,
            "target": 1,
            "curve_type": "Line3DCurveType",
            "length": 1.414213562373095,
            "convexity": "Convex",
            "direction_x": 0.0,
            "direction_y": 0.0,
            "direction_z": 0.0,
            "curvature": 0.0
        },
        {
            "id": 16,
            "source": 8,
            "target": 5,
            "curve_type": "Line3DCurveType",
            "length": 2.0,
            "convexity": "Convex",
            "direction_x": 0.0,
            "direction_y": 0.0,
            "direction_z": 0.0,
            "curvature": 0.0
        },
        {
            "id": 17,
            "source": 8,
            "target": 0,
            "curve_type": "Line3DCurveType",
            "length": 2.0,
            "convexity": "Convex",
            "direction_x": 0.0,
            "direction_y": 0.0,
            "direction_z": 0.0,
            "curvature": 0.0
        },
        {
            "id": 18,
            "source": 8,
            "target": 1,
            "curve_type": "Line3DCurveType",
            "length": 2.0,
            "convexity": "Convex",
            "direction_x": 0.0,
            "direction_y": 0.0,
            "direction_z": 0.0,
            "curvature": 0.0
        },
        {
            "id": 19,
            "source": 9,
            "target": 8,
            "curve_type": "Line3DCurveType",
            "length": 2.0,
            "convexity": "Convex",
            "direction_x": 0.0,
            "direction_y": 0.0,
            "direction_z": 0.0,
            "curvature": 0.0
        },
        {
            "id": 20,
            "source": 9,
            "target": 0,
            "curve_type": "Line3DCurveType",
            "length": 1.414213562373095,
            "convexity": "Convex",
            "direction_x": 0.0,
            "direction_y": 0.0,
            "direction_z": 0.0,
            "curvature": 0.0
        },
        {
            "id": 21,
            "source": 9,
            "target": 1,
            "curve_type": "Line3DCurveType",
            "length": 1.414213562373095,
            "convexity": "Convex",
            "direction_x": 0.0,
            "direction_y": 0.0,
            "direction_z": 0.0,
            "curvature": 0.0
        },
        {
            "id": 22,
            "source": 2,
            "target": 9,
            "curve_type": "Line3DCurveType",
            "length": 2.0,
            "convexity": "Convex",
            "direction_x": 0.0,
            "direction_y": 0.0,
            "direction_z": 0.0,
            "curvature": 0.0
        },
        {
            "id": 23,
            "source": 2,
            "target": 0,
            "curve_type": "Line3DCurveType",
            "length": 2.0,
            "convexity": "Convex",
            "direction_x": 0.0,
            "direction_y": 0.0,
            "direction_z": 0.0,
            "curvature": 0.0
        },
        {
            "id": 24,
            "source": 2,
            "target": 1,
            "curve_type": "Line3DCurveType",
            "length": 2.0,
            "convexity": "Convex",
            "direction_x": 0.0,
            "direction_y": 0.0,
            "direction_z": 0.0,
            "curvature": 0.0
        },
        {
            "id": 25,
            "source": 3,
            "target": 2,
            "curve_type": "Line3DCurveType",
            "length": 2.0,
            "convexity": "Convex",
            "direction_x": 0.0,
            "direction_y": 0.0,
            "direction_z": 0.0,
            "curvature": 0.0
        },
        {
            "id": 26,
            "source": 3,
            "target": 0,
            "curve_type": "Line3DCurveType",
            "length": 1.414213562373095,
            "convexity": "Convex",
            "direction_x": 0.0,
            "direction_y": 0.0,
            "direction_z": 0.0,
            "curvature": 0.0
        },
        {
            "id": 27,
            "source": 3,
            "target": 1,
            "curve_type": "Line3DCurveType",
            "length": 1.414213562373095,
            "convexity": "Convex",
            "direction_x": 0.0,
            "direction_y": 0.0,
            "direction_z": 0.0,
            "curvature": 0.0
        },
        {
            "id": 28,
            "source": 6,
            "target": 3,
            "curve_type": "Line3DCurveType",
            "length": 2.0,
            "convexity": "Convex",
            "direction_x": 0.0,
            "direction_y": 0.0,
            "direction_z": 0.0,
            "curvature": 0.0
        },
        {
            "id": 29,
            "source": 6,
            "target": 0,
            "curve_type": "Line3DCurveType",
            "length": 2.0,
            "convexity": "Convex",
            "direction_x": 0.0,
            "direction_y": 0.0,
            "direction_z": 0.0,
            "curvature": 0.0
        },
        {
            "id": 30,
            "source": 6,
            "target": 1,
            "curve_type": "Line3DCurveType",
            "length": 2.0,
            "convexity": "Convex",
            "direction_x": 0.0,
            "direction_y": 0.0,
            "direction_z": 0.0,
            "curvature": 0.0
        },
        {
            "id": 31,
            "source": 7,
            "target": 6,
            "curve_type": "Line3DCurveType",
            "length": 2.0,
            "convexity": "Convex",
            "direction_x": 0.0,
            "direction_y": 0.0,
            "direction_z": 0.0,
            "curvature": 0.0
        },
        {
            "id": 32,
            "source": 7,
            "target": 0,
            "curve_type": "Line3DCurveType",
            "length": 1.414213562373095,
            "convexity": "Convex",
            "direction_x": 0.0,
            "direction_y": 0.0,
            "direction_z": 0.0,
            "curvature": 0.0
        },
        {
            "id": 33,
            "source": 7,
            "target": 1,
            "curve_type": "Line3DCurveType",
            "length": 1.414213562373095,
            "convexity": "Convex",
            "direction_x": 0.0,
            "direction_y": 0.0,
            "direction_z": 0.0,
            "curvature": 0.0
        }
    ]
}